proto/__init__.py
proto/clients/__init__.py
proto/clients/client_pb2.py
proto/conditions/__init__.py
proto/conditions/notifyCondition_pb2.py
proto/dataStructure/__init__.py
proto/dataStructure/buttonEventType_pb2.py
proto/dataStructure/color_pb2.py
proto/dataStructure/handGestureType_pb2.py
proto/dataStructure/image_pb2.py
proto/dataStructure/keyEvent_pb2.py
proto/dataStructure/lists_pb2.py
proto/dataStructure/matrix3x2_pb2.py
proto/dataStructure/matrix4x4_pb2.py
proto/dataStructure/mouseEvent_pb2.py
proto/dataStructure/myoEvent_pb2.py
proto/dataStructure/object2d_pb2.py
proto/dataStructure/object3d_pb2.py
proto/dataStructure/pose2d_pb2.py
proto/dataStructure/pose3d_pb2.py
proto/dataStructure/quaternion_pb2.py
proto/dataStructure/touchEvent_pb2.py
proto/dataStructure/vector2_pb2.py
proto/dataStructure/vector3_pb2.py
proto/dataStructure/vector4_pb2.py
proto/dataStructure/vector8_pb2.py
proto/devices/__init__.py
proto/devices/component_pb2.py
proto/devices/device_pb2.py
proto/devices/topicDemux_pb2.py
proto/devices/topicMux_pb2.py
proto/general/__init__.py
proto/general/error_pb2.py
proto/general/success_pb2.py
proto/processing/__init__.py
proto/processing/lockstepProcessing_pb2.py
proto/processing/processingModule_pb2.py
proto/servers/__init__.py
proto/servers/server_pb2.py
proto/services/__init__.py
proto/services/serviceReply_pb2.py
proto/services/serviceRequest_pb2.py
proto/services/service_pb2.py
proto/services/request/__init__.py
proto/services/request/topicSubscription_pb2.py
proto/sessions/__init__.py
proto/sessions/ioMappings_pb2.py
proto/sessions/session_pb2.py
proto/topicData/__init__.py
proto/topicData/timestamp_pb2.py
proto/topicData/topicDataRecord_pb2.py
proto/topicData/topicDataSource_pb2.py
proto/topicData/topicData_pb2.py
Ubii_Python_Protofiles-0.1.1.dist-info/LICENSE.txt
Ubii_Python_Protofiles-0.1.1.dist-info/METADATA
Ubii_Python_Protofiles-0.1.1.dist-info/WHEEL
Ubii_Python_Protofiles-0.1.1.dist-info/top_level.txt
Ubii_Python_Protofiles-0.1.1.dist-info/RECORD
