Metadata-Version: 2.1
Name: Ubii-Python-Protofiles
Version: 0.1.1
Summary: Ubii Message Protobuf files compiled for python
Home-page: https://github.com/SandroWeber/ubii-msg-formats
Author: Anian Kalb
Author-email: ge38tak@mytum.de
Classifier: Programming Language :: Python :: 3
Requires-Python: >=3.7
License-File: LICENSE.txt
Requires-Dist: protobuf ==3.20
